afilnet
