Metadata-Version: 1.1
Name: afilnet
Version: 0.1.4.6.1
Summary: This package is an easy way to use send sms, email and voice(texto-to-speech) using Afilnet services
Home-page: http://github.com/afilnet/api-python
Author: Afilnet Cloud Marketing
Author-email: soporte@afilnet.com
License: MIT
Keywords: afilnet sms email voice message phone call notification cloud marketing service
Platform: UNKNOWN
Classifier: Development Status :: 4 - Beta
Classifier: Intended Audience :: Telecommunications Industry
Classifier: Intended Audience :: Customer Service
Classifier: Intended Audience :: Developers
Classifier: License :: OSI Approved :: MIT License
Classifier: Programming Language :: Python :: 2
Classifier: Programming Language :: Python :: 2.6
Classifier: Programming Language :: Python :: 2.7
Classifier: Programming Language :: Python :: 3
Classifier: Programming Language :: Python :: 3.3
Classifier: Programming Language :: Python :: 3.4
Classifier: Programming Language :: Python :: 3.5
